bigquery_builder/__init__.py
bigquery_builder/build.py
bigquery_builder-0.1.1.dist-info/LICENSE
bigquery_builder-0.1.1.dist-info/METADATA
bigquery_builder-0.1.1.dist-info/WHEEL
bigquery_builder-0.1.1.dist-info/top_level.txt
bigquery_builder-0.1.1.dist-info/RECORD
