Metadata-Version: 2.1
Name: bigquery-builder
Version: 0.1.1
Summary: X-I-A Library - Google Cloud Storage Modules
Home-page: https://github.com/X-I-A/bigquery-builder
Author: Soral
Author-email: soral@x-i-a.com
License: UNKNOWN
Platform: UNKNOWN
Classifier: Programming Language :: Python :: 3
Classifier: License :: OSI Approved :: GNU General Public License v3 (GPLv3)
Classifier: Operating System :: OS Independent
Requires-Python: >=3.7
Requires-Dist: google-auth
Requires-Dist: google-cloud-bigquery
Requires-Dist: Markdown
